setup.py
chunks/__init__.py
chunks.egg-info/PKG-INFO
chunks.egg-info/SOURCES.txt
chunks.egg-info/dependency_links.txt
chunks.egg-info/top_level.txt
chunks.egg-info/zip-safe