Metadata-Version: 1.0
Name: chunks
Version: 0.1
Summary: Encode and decode http chunked encoding.
Home-page: http://www.engledew.com
Author: Simon Engledew
Author-email: simon@engledew.com
License: MIT
Keywords: chunked,http,chunks,encoding,decode
Platform: UNKNOWN
Classifier: Development Status :: 1 - Planning
Classifier: Operating System :: OS Independent
Classifier: Programming Language :: Python
